README.md
recursive_yaml.py
setup.py
recursive_yaml.egg-info/PKG-INFO
recursive_yaml.egg-info/SOURCES.txt
recursive_yaml.egg-info/dependency_links.txt
recursive_yaml.egg-info/entry_points.txt
recursive_yaml.egg-info/requires.txt
recursive_yaml.egg-info/top_level.txt