Metadata-Version: 1.0
Name: recursive-yaml
Version: 0.0.1
Summary: Load YAML Recursively
Home-page: https://github.com/FebruaryBreeze/recursive-yaml
Author: SF-Zhou
Author-email: sfzhou.scut@gmail.com
License: UNKNOWN
Keywords: Recursive YAML
Platform: UNKNOWN
